pygit/__init__.py
pygit/__main__.py
pygit/__version__.py
pygit/pygit.py
pygit/test.py
python_git-2018.2.1.dist-info/LICENSE.txt
python_git-2018.2.1.dist-info/METADATA
python_git-2018.2.1.dist-info/WHEEL
python_git-2018.2.1.dist-info/top_level.txt
python_git-2018.2.1.dist-info/RECORD
