Metadata-Version: 1.1
Name: python-git
Version: 2018.2.1
Summary: Automate boring git tasks
Home-page: https://github.com/chidimo/python-git
Author: Chidi Orji
Author-email: orjichidi95@gmail.com
License: MIT
Download-URL: https://github.com/chidimo/python-git/archive/master.zip
Keywords: automate boring git and github tasks
Platform: UNKNOWN
Classifier: Development Status :: 5 - Production/Stable
Classifier: Programming Language :: Python :: 3.6
Classifier: License :: OSI Approved :: MIT License
Classifier: Intended Audience :: Developers
Classifier: Natural Language :: English
Classifier: Operating System :: POSIX :: Linux
Classifier: Operating System :: Microsoft :: Windows :: Windows 10
Classifier: Topic :: Software Development :: Version Control :: Git
Classifier: Topic :: Utilities
